contentor_video_processor/__init__.py
contentor_video_processor/apps.py
contentor_video_processor/context_processor.py
contentor_video_processor/fields.py
contentor_video_processor/files.py
contentor_video_processor/functions.py
contentor_video_processor/models.py
contentor_video_processor/storage.py
contentor_video_processor/urls.py
contentor_video_processor/validators.py
contentor_video_processor/views.py
contentor_video_processor/widgets.py
contentor_video_processor/migrations/__init__.py
contentor_video_processor/static/contentor_video_processor/js/resumable.js
contentor_video_processor/templates/contentor_video_processor/admin_file_input.html
contentor_video_processor/templates/contentor_video_processor/user_file_input.html
contentor_video_processor/templates/contentor_video_processor/video_element.html
contentor_video_processor/templatetags/__init__.py
contentor_video_processor/templatetags/resolution_filter.py
django_contentor_video_processor-0.9.2.dist-info/licenses/LICENSE
django_contentor_video_processor-0.9.2.dist-info/METADATA
django_contentor_video_processor-0.9.2.dist-info/WHEEL
django_contentor_video_processor-0.9.2.dist-info/top_level.txt
django_contentor_video_processor-0.9.2.dist-info/RECORD
